icdmappings/__init__.py
icdmappings/data_files/CCIR_v2023-1.csv
icdmappings/data_files/CCS-SingleDiagnosisGrouper.txt
icdmappings/data_files/DXCCSR_v2023-1.csv
icdmappings/data_files/ICD10_CM_CCSR/__init__.py
icdmappings/data_files/ICD10_CM_CCSR/dx_cat1_mapping.json
icdmappings/data_files/ICD10_CM_Chapters/__init__.py
icdmappings/data_files/ICD10_CM_Chapters/chapter_lookup.json
icdmappings/data_files/ICD10_CM_Chapters/chapter_name_lookup.json
icdmappings/data_files/ICD_10_CM_2024_release/__init__.py
icdmappings/data_files/ICD_10_CM_2024_release/icd10cm-codes-2024.txt
icdmappings/data_files/ICD_10_CM_2024_release/icd10pcs-codes-2024.txt
icdmappings/data_files/ICD_10_CM_2024_release/readme.md
icdmappings/data_files/ICD_9_CM_v32_master_descriptions/CMS32_DESC_LONG_DX.txt
icdmappings/data_files/ICD_9_CM_v32_master_descriptions/CMS32_DESC_LONG_SG.txt
icdmappings/data_files/ICD_9_CM_v32_master_descriptions/CMS32_DESC_SHORT_DX.txt
icdmappings/data_files/ICD_9_CM_v32_master_descriptions/CMS32_DESC_SHORT_SG.txt
icdmappings/data_files/ICD_9_CM_v32_master_descriptions/__init__.py
icdmappings/data_files/ICD_9_CM_v32_master_descriptions/readme.md
icdmappings/data_files/__init__.py
icdmappings/data_files/cci2015.csv
icdmappings/data_files/icd10-chapters.csv
icdmappings/data_files/icd10cmtoicd9gem.csv
icdmappings/data_files/icd9-CM-code-chapter-en=PT.csv
icdmappings/data_files/icd9dx2015.csv
icdmappings/data_files/icd9toicd10cmgem.csv
icdmappings/icdmappings.py
icdmappings/mappers/__init__.py
icdmappings/mappers/icd10_to_ccir.py
icdmappings/mappers/icd10_to_ccsr.py
icdmappings/mappers/icd10_to_chapters.py
icdmappings/mappers/icd10_to_icd9.py
icdmappings/mappers/icd9_to_cci.py
icdmappings/mappers/icd9_to_ccs.py
icdmappings/mappers/icd9_to_chapters.py
icdmappings/mappers/icd9_to_icd10.py
icdmappings/mappers/mapper_interface.py
icdmappings/validators/__init__.py
icdmappings/validators/icd10_validator.py
icdmappings/validators/icd9_validator.py
icd_mappings-0.3.8.dist-info/METADATA
icd_mappings-0.3.8.dist-info/WHEEL
icd_mappings-0.3.8.dist-info/RECORD
