Metadata-Version: 2.1
Name: icd-mappings
Version: 0.3.8
Summary: This python tool enables a variety of mappings between ICD diagnostic codes (International Classification of Diseases) with a single line of code.
Home-page: https://github.com/snovaisg/ICDMappings
License: MIT
Author: Simao Novais
Author-email: snovaisg.97@gmail.com
Requires-Python: >=3.8,<4.0
Classifier: License :: OSI Approved :: MIT License
Classifier: Programming Language :: Python :: 3
Classifier: Programming Language :: Python :: 3.8
Classifier: Programming Language :: Python :: 3.9
Classifier: Programming Language :: Python :: 3.10
Classifier: Programming Language :: Python :: 3.11
Requires-Dist: importlib-resources (>=5.12.0,<6.0.0)
Project-URL: Repository, https://github.com/snovaisg/ICDMappings
